{
  "credit": "Made by Metla for MovieMod",
  "parent": "minecraft:item/generated",
  "textures": {
    "layer0": "moviemod:item/domination_sphere"
  },
  "elements": [
    {
      "name": "sphere",
      "from": [5, 5, 5],
      "to": [11, 11, 11],
      "faces": {
        "north": {"uv": [0, 0, 6, 6], "texture": "#layer0"},
        "east": {"uv": [0, 0, 6, 6], "texture": "#layer0"},
        "south": {"uv": [0, 0, 6, 6], "texture": "#layer0"},
        "west": {"uv": [0, 0, 6, 6], "texture": "#layer0"},
        "up": {"uv": [0, 0, 6, 6], "texture": "#layer0"},
        "down": {"uv": [0, 0, 6, 6], "texture": "#layer0"}
      }
    }
  ],
  "display": {
    "thirdperson_righthand": {
      "rotation": [75, 45, 0],
      "translation": [0, 2.5, 2.5],
      "scale": [0.5, 0.5, 0.5]
    },
    "thirdperson_lefthand": {
      "rotation": [75, 45, 0],
      "translation": [0, 2.5, 2.5],
      "scale": [0.5, 0.5, 0.5]
    },
    "firstperson_righthand": {
      "rotation": [0, 45, 0],
      "translation": [0, 4, 0],
      "scale": [0.7, 0.7, 0.7]
    },
    "firstperson_lefthand": {
      "rotation": [0, 45, 0],
      "translation": [0, 4, 0],
      "scale": [0.7, 0.7, 0.7]
    },
    "ground": {
      "translation": [0, 3, 0],
      "scale": [0.5, 0.5, 0.5]
    },
    "gui": {
      "rotation": [30, 225, 0],
      "translation": [0, 0, 0],
      "scale": [0.8, 0.8, 0.8]
    },
    "head": {
      "translation": [0, 12, 0],
      "scale": [1, 1, 1]
    },
    "fixed": {
      "rotation": [0, 0, 0],
      "translation": [0, 0, 0],
      "scale": [0.8, 0.8, 0.8]
    }
  }
} 